{
  "unversionedId": "channel-line-setup",
  "id": "channel-line-setup",
  "isDocsHomePage": false,
  "title": "LINE Setup",
  "description": "Enabling LINE Channels",
  "source": "@site/../docs/channel-line-setup.md",
  "sourceDirName": ".",
  "slug": "/channel-line-setup",
  "permalink": "/docs/next/channel-line-setup",
  "editUrl": "https://github.com/Yoctol/bottender/edit/master/docs/../docs/channel-line-setup.md",
  "tags": [],
  "version": "current",
  "lastUpdatedBy": "Author",
  "lastUpdatedAt": 1539502055,
  "formattedLastUpdatedAt": "10/14/2018",
  "frontMatter": {
    "id": "channel-line-setup",
    "title": "LINE Setup"
  },
  "sidebar": "docs",
  "previous": {
    "title": "WhatsApp Routing",
    "permalink": "/docs/next/channel-whatsapp-routing"
  },
  "next": {
    "title": "Handling LINE Events",
    "permalink": "/docs/next/channel-line-handling-events"
  }
}