{
  "unversionedId": "api-line-client",
  "id": "api-line-client",
  "isDocsHomePage": false,
  "title": "LineClient",
  "description": "- Usage",
  "source": "@site/../docs/api-line-client.md",
  "sourceDirName": ".",
  "slug": "/api-line-client",
  "permalink": "/docs/next/api-line-client",
  "editUrl": "https://github.com/Yoctol/bottender/edit/master/docs/../docs/api-line-client.md",
  "tags": [],
  "version": "current",
  "lastUpdatedBy": "Author",
  "lastUpdatedAt": 1539502055,
  "formattedLastUpdatedAt": "10/14/2018",
  "frontMatter": {
    "id": "api-line-client",
    "title": "LineClient"
  },
  "sidebar": "api",
  "previous": {
    "title": "LineEvent",
    "permalink": "/docs/next/api-line-event"
  },
  "next": {
    "title": "SlackContext",
    "permalink": "/docs/next/api-slack-context"
  }
}